oauth2py
