Metadata-Version: 1.1
Name: oauth2py
Version: 1.1.4
Summary: a simple, lightweight oauth client
Home-page: https://github.com/caoyue/oauth2py
Author: caoyue
Author-email: i@caoyue.me
License: http://www.apache.org/licenses/LICENSE-2.0
Download-URL: https://github.com/caoyue/oauth2py
Platform: UNKNOWN
Classifier: License :: OSI Approved :: Apache Software License
Classifier: Programming Language :: Python :: 2.7
Classifier: Programming Language :: Python :: Implementation :: CPython
Classifier: Programming Language :: Python :: Implementation :: PyPy
